setup.py
vgrid/__init__.py
vgrid/interval_block.py
vgrid/label_state.py
vgrid/metadata.py
vgrid/spatial_type.py
vgrid/spec.py
vgrid/vis_format.py
vgridpy.egg-info/PKG-INFO
vgridpy.egg-info/SOURCES.txt
vgridpy.egg-info/dependency_links.txt
vgridpy.egg-info/not-zip-safe
vgridpy.egg-info/requires.txt
vgridpy.egg-info/top_level.txt