Metadata-Version: 1.0
Name: vgridpy
Version: 0.1.13
Summary: Python bindings into Vgrid objects
Home-page: http://github.com/scanner-research/vgrid
Author: Xinwei Yao, Will Crichton
Author-email: yaodavid@stanford.edu
License: Apache 2.0
Platform: UNKNOWN
